editorialmanager/__init__.py
editorialmanager/version.py
editorialmanager-0.1.1.dist-info/LICENSE
editorialmanager-0.1.1.dist-info/METADATA
editorialmanager-0.1.1.dist-info/WHEEL
editorialmanager-0.1.1.dist-info/top_level.txt
editorialmanager-0.1.1.dist-info/RECORD
