Metadata-Version: 2.1
Name: editorialmanager
Version: 0.1.1
Summary: Python interface for querying the editorial manager journal submission system
Home-page: https://github.com/glichtner/pyeditorialmanager
Author: Gregor Lichtner
Author-email: UNKNOWN
License: GPL v3
Platform: UNKNOWN
Requires-Dist: pandas
Requires-Dist: beautifulsoup4
Requires-Dist: html5lib
